<?xml version="1.0" encoding="UTF-8"?>
<text xmlns="http://www.tei-c.org/ns/1.0" xml:base="https://betamasaheft.eu/">
   <body>
      <div type="edition" xml:id="Transkribus" subtype="transkribus">
         <div type="textpart" subtype="image" n="1">
            <ab>
               <pb facs="#facs_1" n="1r"/>
               <cb facs="#facs_1_TextRegion_1724838026120_102" n="a"/>
               <lb facs="#facs_1_line_1724838030092_106" n="1" break="no"/>በሰመ፡ እግዚአብሔር፡ሀያው</ab>
         </div>
         <div type="textpart" subtype="image" n="2">
            <ab>
               <pb facs="#facs_2" n="2r"/>
               <cb facs="#facs_2_r1" n="a"/>
               <lb facs="#facs_2_r1l6" n="1" break="no"/>ባሰተ፡ ወአንስተ፡ ወበቀዳመ፡
				<lb facs="#facs_2_r1l7" n="2"/>ወራጹ፡ ውርእህልዮ፡ ነቢሱላስሰ፡
				<lb facs="#facs_2_r1l8" n="3"/>ለአራጊት፡ ወትሰቤበአትው፡
				<lb facs="#facs_2_r1l9" n="4"/>አተባነት፡ ዘሃመ፡ በቅድሜከ፡ 
				<lb facs="#facs_2_r1l10" n="5"/>ወቦአትውርዘሐያ፡ ትነበር። ታ<lb facs="#facs_2_r1l11" n="6" break="no"/>ህተአደውየ፡ ከመኢትቅል፡ 
				<lb facs="#facs_2_r1l12" n="7"/>ህፃናተአንሰ፡ ዕከውን፡ ገብርከ፡ 
				<lb facs="#facs_2_r1l13" n="8"/>ወዕከውን፡ ሰማዕተ፡ በእንተ፡ 
				<lb facs="#facs_2_r1l14" n="9"/>አሰስሎ፡ ደዌ፡ እምህፃናት፡ እ<lb facs="#facs_2_r1l15" n="10" break="no"/>ለ፡ ይጠብው፡ ጥበ፡ እሞሙ፡ 
				<lb facs="#facs_2_r1l16" n="11"/>ወኩሎዳዊያት፡ ትጽህፎዓ<lb facs="#facs_2_r1l17" n="12" break="no"/>ዲለብእሲት፡ ወትሰቅሎ፡ ላዕ<lb facs="#facs_2_r1l18" n="13" break="no"/>ሌሃ፡ ወይበቁዕበርድኤተ፡ አግ<lb facs="#facs_2_r1l19" n="14" break="no"/>ዚአብሔር፡ ልዑል፡ ወሠርት፡ 
				<lb facs="#facs_2_r1l20" n="15"/>ወኮልባት፡ ወከራሃት፡ ወበከየ፡ 
				<lb facs="#facs_2_r1l21" n="16"/>ተዕመ፡ ወሶበ፡ ሰምዓ፡ ቅዱስ፡ 
				<lb facs="#facs_2_r1l22" n="17"/>ወሠር፡ ወመጽአ፡ ወረከበለ<lb facs="#facs_2_r1l23" n="18" break="no"/>ውረዘልያነቤሉ፡ ላዕለ፡ አራዒ<lb facs="#facs_2_r1l24" n="19" break="no"/>ት፡ወትቤሎ፡ ቦአት፡ ውስተ፡ ገ<lb facs="#facs_2_r1l25" n="20" break="no"/>ነቅዘሃሎ፡ በቅዱሜከ፡ ወቦአ<lb facs="#facs_2_r1l26" n="21" break="no"/>ትውርዝልያነቢራላዕለአራ<lb facs="#facs_2_r1l27" n="22" break="no"/>ጊትወኑስቅሎ፡ ላዕለ፡ አራጊ<lb facs="#facs_2_r1l28" n="23" break="no"/>ኒጠትቤሎ፡ ቦአትውርዘል<lb facs="#facs_2_r1l29" n="24" break="no"/>ያነቢኦሉ፡ አንዩስ፡ አምሀለ፡
			</ab>
         </div>
         <div type="textpart" subtype="image" n="3">
            <ab>
               <pb facs="#facs_3" n="3r"/>
               <cb facs="#facs_3_r1" n="a"/>
               <lb facs="#facs_3_r1l3" n="1" break="no"/>ከወአወግዚከበ፯መዓርግ፡ 
				<lb facs="#facs_3_r1l4" n="2"/>ሊቃነመላእክት፡ ቅዱስ፡ ሚ<lb facs="#facs_3_r1l5" n="3" break="no"/>ካኤል፡፡ወገንርኤልሱራ<lb facs="#facs_3_r1l7" n="4" break="no"/>ፌልወኪሩቤል[ ]ልአ<lb facs="#facs_3_r1l8" n="5" break="no"/>ልወሩፋኤልአፍኒንልጉኤ<lb facs="#facs_3_r1l9" n="6" break="no"/>ልወሰቁኤል፡ ወሰዳካኤል፡ 
				<lb facs="#facs_3_r1l10" n="7"/>አናንአያወአዛርአ፡ ያወሜሳ<lb facs="#facs_3_r1l11" n="8" break="no"/>ኤልእለ፡ ዕሙንቱ፡ እለ፡ ይቀው<lb facs="#facs_3_r1l12" n="9" break="no"/>ሙ፡ ቅድመ፡ መንበር፡ ለእግዚ<lb facs="#facs_3_r1l13" n="10" break="no"/>አብሔር፡ አለዜኩሉ፡ ዓለም፡ 
				<lb facs="#facs_3_r1l14" n="11"/>ዘልፈእስከ፡ ለዓለመ፡ ዓለም፡ 
				<lb facs="#facs_3_r1l15" n="12"/>ወአፈድፈደ፡ ተነድሎቱ፡ ለሰ<lb facs="#facs_3_r1l16" n="13" break="no"/>መ፡ ኢየሱስ፡ ክርስቶስ፡ ይቀ<lb facs="#facs_3_r1l17" n="14" break="no"/>ባ፡ ወያድህና፡እምበርያወሌጊ<lb facs="#facs_3_r1l18" n="15" break="no"/>ዎን፡ወእምህማመ፡ ስቀላይ፡ 
				<lb facs="#facs_3_r1l19" n="16"/>ወዓይነናሶ፡ ወዛር፡ ወዓይነጥላ፡ 
				<lb facs="#facs_3_r1l20" n="17"/>ወደምአድህና፡ ለዓመትከ፡ በ<lb facs="#facs_3_r1l21" n="18" break="no"/>ፍታ፡ ማሪፋ፡ በፍታ፡ ጸሎቱ፡ 
				<lb facs="#facs_3_r1l22" n="19"/>በእንተ፡ህማመ፡ ጽንሰት፡ ብ<lb facs="#facs_3_r1l23" n="20" break="no"/>ፁዕብእሲተ፡ ዘኢሠርበም<lb facs="#facs_3_r1l24" n="21" break="no"/>ክረ፡ ረሴአን፡ ወዘኢቆመ፡ ው<lb facs="#facs_3_r1l25" n="22" break="no"/>አትፍኖተ፡ ኃጥአን፡ ወዘኢነበ<lb facs="#facs_3_r1l26" n="23" break="no"/>ረውስተ፡ መንበረ፡ መስተሣ<lb facs="#facs_3_r1l27" n="24" break="no"/>ልቃን፡ ዘዳዕሙ፡ ሕገ፡ እግዚ<lb facs="#facs_3_r1l28" n="25" break="no"/>አብሔር፡ ሥምርቱ፡ ወዘሕጉ</ab>
         </div>
         <div type="textpart" subtype="image" n="4">
            <ab>
               <pb facs="#facs_4" n="4r"/>
               <cb facs="#facs_4_r1" n="a"/>
               <lb facs="#facs_4_r1l3" n="1" break="no"/>ያነብብ፡ መዓልተ፡ ወሌሌተ፡ 
				<lb facs="#facs_4_r1l4" n="2"/>ወይከውንከመ፡ ፅፅአንተ፡ 
				<lb facs="#facs_4_r1l6" n="3"/>ትረከልትኃዐ፡ ሙሐዘ፡ ማይ፡ 
				<lb facs="#facs_4_r1l7" n="4"/>እንተ፡ ትሁብ፡ ፍሬሃ፡ በበጊዜ<lb facs="#facs_4_r1l8" n="5" break="no"/>ሃ፡ ወቆጽላኒ፡ ኢይትነገፍ፡ ከማ<lb facs="#facs_4_r1l9" n="6" break="no"/>ሁ፡ ኢይንግፍ፡ ዩሬ፡ ማህጸና፡ 
				<lb facs="#facs_4_r1l10" n="7"/>በወሌዳህና፡ ከማሁ፡ ትሰለድ፡ 
				<lb facs="#facs_4_r1l11" n="8"/>ወወሊደ፡ ወልድ፡ ከማሁ፡ ትሰ<lb facs="#facs_4_r1l12" n="9" break="no"/>ለድ፡ ወልዳ፡ ዓመትከ፡ መነን፡ 
				<lb facs="#facs_4_r1l13" n="10"/>(ግዘሙ ለአጋንንንት) በሰመአብ፡ በወወልደ፡ ወመን<lb facs="#facs_4_r1l14" n="11" break="no"/>ፈስ፡ ቅዱስ፡ ፩አምላክ፡ ጸሎት፡፡በ<lb facs="#facs_4_r1l15" n="12" break="no"/>እንተህማመ፡ ማዕሠረነነ፡ 
				<lb facs="#facs_4_r1l16" n="13"/>መስጥም፡ ዘበርያመ፡ ስጥም፡ 
				<lb facs="#facs_4_r1l17" n="14"/>ዘሌጌዎን፡ መስጥም፡ ዘነገር<lb facs="#facs_4_r1l18" n="15" break="no"/>ኃር፡ ሀርበዳሙ፡ ሀርበደ፡ውሀ<lb facs="#facs_4_r1l19" n="16" break="no"/>ርበዳው፡ ሀርበደው፡ ሀርበደ<lb facs="#facs_4_r1l20" n="17" break="no"/>ወሀርበደው፡ ሐርዥ፡ በትሐ<lb facs="#facs_4_r1l21" n="18" break="no"/>ርዥ በትሐርዥበት፡ በርዥበ<lb facs="#facs_4_r1l22" n="19" break="no"/>ትበርሀዥርአንተ፡ ቁም፡ ንጉ<lb facs="#facs_4_r1l23" n="20" break="no"/>ሦሙ፡ ለአጋንንት፡ አቅትለኔ፡ 
				<lb facs="#facs_4_r1l24" n="21"/>አግሩጣ፡ የሐልዩ፡ ይዴ፡ ማ<lb facs="#facs_4_r1l25" n="22" break="no"/>ህዴጅሀም፡ አሙ፡ አስክለ፡ 
				<lb facs="#facs_4_r1l26" n="23"/>አግሩጣኤላምኔአህላወስህላ፡ 
				<lb facs="#facs_4_r1l27" n="24"/>እዝዝ፡ ወከርሞ፡ ብሁም፡ ሰም<lb facs="#facs_4_r1l28" n="25" break="no"/>ኖንነዎሀድ፡ አብሐብዱሙ፡
			</ab>
         </div>
         <div type="textpart" subtype="image" n="5">
            <ab>
               <pb facs="#facs_5" n="5r"/>
               <cb facs="#facs_5_r1" n="a"/>
               <lb facs="#facs_5_r1l1" n="1" break="no"/>
               <lb facs="#facs_5_r1l4" n="2" break="no"/>ጋኢ፡ ወያኤርር በምድረ፡ ፈግ<lb facs="#facs_5_r1l5" n="3" break="no"/>ኆዥቄአጋንንት፡ እግፋጣኤ<lb facs="#facs_5_r1l6" n="4" break="no"/>ለሞአህለ ወሳህላአአ፡ ወከ<lb facs="#facs_5_r1l7" n="5" break="no"/>ረም፡ ብሁሞ፡ በዘንቱ፡ አሰማ<lb facs="#facs_5_r1l8" n="6" break="no"/>ቲከዘኤወስካለቲ፡ ለአዳም፡
				<lb facs="#facs_5_r1l9" n="7"/>መስሔዋን፡ ለሰራ፡ ወለአብ<lb facs="#facs_5_r1l10" n="8" break="no"/>ርሃም፡ ከማሆሙ፡ አድህና፡
				<lb facs="#facs_5_r1l11" n="9"/>ለዓመትከ፡አኩ[ ]ን፡ በመለከ፡
			</ab>
         </div>
         <div type="textpart" subtype="image" n="6">
            <ab>
               <pb facs="#facs_6" n="6r"/>
               <cb facs="#facs_7_r1" n="a"/>
               <lb facs="#facs_7_r1l1" n="1" break="no"/>በሰመአበ፡ ወወልድ፡ ወመን<lb facs="#facs_7_r1l2" n="2" break="no"/>ፈስቅዱስ ፩አምላክ፡ ጸሎት፡ በ<lb facs="#facs_7_r1l3" n="3" break="no"/>አንተህጠመ፡ መፍቅሄ፡ ሥ<lb facs="#facs_7_r1l4" n="4" break="no"/>ፍይአይበአአ፡ አይበሪስ እግ<lb facs="#facs_7_r1l5" n="5" break="no"/>በእረ፡ አይባእስአ፡ ይፀእስኤ<lb facs="#facs_7_r1l6" n="6" break="no"/>መርታ፡ ደምርተደምሌታ፡ 
				<lb facs="#facs_7_r1l7" n="7"/>መርቃያሞ፡ አከለ፡ በክረከ<lb facs="#facs_7_r1l8" n="8" break="no"/>ከአክሎ፡ስ፡ሎ<lb facs="#facs_7_r1l9" n="9" break="no"/>እሎከ፡ ገርሁ፡ንገሪሆን<lb facs="#facs_7_r1l10" n="10" break="no"/>ገሪሆንገዕወሁህና፡ 
				<lb facs="#facs_7_r1l11" n="11"/>እምህጠመ፡ መፍትሒ፡ 
				<lb facs="#facs_7_r1l12" n="12"/>ሠራይ፡ በዓመት፡ ከማነን፡ 
				<lb facs="#facs_7_r1l13" n="13"/>ምነን።ወአወወል<lb facs="#facs_7_r1l14" n="14" break="no"/>ዱ፡ ወበመንፈቅትዱ፡ ፩እም<lb facs="#facs_7_r1l15" n="15" break="no"/>ጸመት፡ በእንተ፡ ህማ<lb facs="#facs_7_r1l16" n="16" break="no"/>መ፡ ለዳመ፡ አንተሞ፡ ከንተ<lb facs="#facs_7_r1l17" n="17" break="no"/>ም፡ ከንቶሞ፡ አንተም፡ ክን<lb facs="#facs_7_r1l18" n="18" break="no"/>ተሞሰንኑም፡ ሰንተምከ<lb facs="#facs_7_r1l19" n="19" break="no"/>ንተሞ፡ ሰንተሞ፡ ክተምሌ<lb facs="#facs_7_r1l20" n="20" break="no"/>አፍቤለሲኦአፍሌል፡ ሊሰ<lb facs="#facs_7_r1l21" n="21" break="no"/>አፍሴአ ኢአሌል፡ ኦፍቤላ፡ 
				<lb facs="#facs_7_r1l22" n="22"/>ኢአ ኦ ፍቤሰ፡ መሌሰ፡ መለል<lb facs="#facs_7_r1l23" n="23" break="no"/>ከ፡ ዘዓረባዕከ። ይለስና፡
				<lb facs="#facs_7_r1l24" n="24"/>ነፍሰ፡ ከማሁ፡ ዓርማዕ፡ ይመ<lb facs="#facs_7_r1l25" n="25" break="no"/>ለዓመተከ፡ በፍታ፡ ማሪፍፋ፡ 
				<lb facs="#facs_7_r1l26" n="26"/>ጸሎት፡ በእንተ፡ ህማመ፡ ዓይ</ab>
         </div>
         <div type="textpart" subtype="image" n="7">
            <ab>
               <pb facs="#facs_7" n="7r"/>
               <cb facs="#facs_7_r1" n="a"/>
               <lb facs="#facs_7_r1l1" n="1" break="no"/>በሰመአበ፡ ወወልድ፡ ወመን<lb facs="#facs_7_r1l2" n="2" break="no"/>ፈስቅዱስ ፩አምላክ፡ ጸሎት፡ በ<lb facs="#facs_7_r1l3" n="3" break="no"/>አንተህጠመ፡ መፍቅሄ፡ ሥ<lb facs="#facs_7_r1l4" n="4" break="no"/>ፍይአይበአአ፡ አይበሪስ እግ<lb facs="#facs_7_r1l5" n="5" break="no"/>በእረ፡ አይባእስአ፡ ይፀእስኤ<lb facs="#facs_7_r1l6" n="6" break="no"/>መርታ፡ ደምርተደምሌታ፡ 
				<lb facs="#facs_7_r1l7" n="7"/>መርቃያሞ፡ አከለ፡ በክረከ<lb facs="#facs_7_r1l8" n="8" break="no"/>ከአክሎ፡ስ፡ሎ<lb facs="#facs_7_r1l9" n="9" break="no"/>እሎከ፡ ገርሁ፡ንገሪሆን<lb facs="#facs_7_r1l10" n="10" break="no"/>ገሪሆንገዕወሁህና፡ 
				<lb facs="#facs_7_r1l11" n="11"/>እምህጠመ፡ መፍትሒ፡ 
				<lb facs="#facs_7_r1l12" n="12"/>ሠራይ፡ በዓመት፡ ከማነን፡ 
				<lb facs="#facs_7_r1l13" n="13"/>ምነን።ወአወወል<lb facs="#facs_7_r1l14" n="14" break="no"/>ዱ፡ ወበመንፈቅትዱ፡ ፩እም<lb facs="#facs_7_r1l15" n="15" break="no"/>ጸመት፡ በእንተ፡ ህማ<lb facs="#facs_7_r1l16" n="16" break="no"/>መ፡ ለዳመ፡ አንተሞ፡ ከንተ<lb facs="#facs_7_r1l17" n="17" break="no"/>ም፡ ከንቶሞ፡ አንተም፡ ክን<lb facs="#facs_7_r1l18" n="18" break="no"/>ተሞሰንኑም፡ ሰንተምከ<lb facs="#facs_7_r1l19" n="19" break="no"/>ንተሞ፡ ሰንተሞ፡ ክተምሌ<lb facs="#facs_7_r1l20" n="20" break="no"/>አፍቤለሲኦአፍሌል፡ ሊሰ<lb facs="#facs_7_r1l21" n="21" break="no"/>አፍሴአ ኢአሌል፡ ኦፍቤላ፡ 
				<lb facs="#facs_7_r1l22" n="22"/>ኢአ ኦ ፍቤሰ፡ መሌሰ፡ መለል<lb facs="#facs_7_r1l23" n="23" break="no"/>ከ፡ ዘዓረባዕከ። ይለስና፡
				<lb facs="#facs_7_r1l24" n="24"/>ነፍሰ፡ ከማሁ፡ ዓርማዕ፡ ይመ<lb facs="#facs_7_r1l25" n="25" break="no"/>ለዓመተከ፡ በፍታ፡ ማሪፍፋ፡ 
				<lb facs="#facs_7_r1l26" n="26"/>ጸሎት፡ በእንተ፡ ህማመ፡ ዓይ</ab>
         </div>
         <div type="textpart" subtype="image" n="8">
            <ab>
               <pb facs="#facs_8" n="8r"/>
               <cb facs="#facs_8_r1" n="a"/>
               <lb facs="#facs_8_r1l3" n="1" break="no"/>ነጥላ፡ አግዚ፡ ኦእግዚአነን።
				<lb facs="#facs_8_r1l4" n="2"/>ተሰብሐስምከ፡ በኵሉም<lb facs="#facs_8_r1l5" n="3" break="no"/>ድር፡ እስመ፡ ተአላአለዕስየሰ<lb facs="#facs_8_r1l6" n="4" break="no"/>ባሐቲከመልሰራሩ፡ ሰማ<lb facs="#facs_8_r1l7" n="5" break="no"/>ያትእምአኤ፡ ደቂቅ፡ ወህፃና<lb facs="#facs_8_r1l8" n="6" break="no"/>ት፡ አስተዳሎከ፡ አብሐተበእ<lb facs="#facs_8_r1l9" n="7" break="no"/>ንተጸላኢ፡ ከመትንስቶለጊ<lb facs="#facs_8_r1l10" n="8" break="no"/>ላኢወለገፋኢ፡ እስመ፡ ንፍ<lb facs="#facs_8_r1l11" n="9" break="no"/>አሰማያተ፡ ግብርአንብአ<lb facs="#facs_8_r1l12" n="10" break="no"/>ዓ፡ ወርሀጠከዋክቦተ፡ ዘለ<lb facs="#facs_8_r1l13" n="11" break="no"/>ሌከ፡ ሣርርከ፡ ምንትኑ፡ አ<lb facs="#facs_8_r1l14" n="12" break="no"/>ንለእመሕያው፡ ከመ፡ ተሀ<lb facs="#facs_8_r1l15" n="13" break="no"/>ው፡ ፃሕተ፡ አህጸጹስ፡ እመ<lb facs="#facs_8_r1l16" n="14" break="no"/>ላእክቲከከብረወአብሐ<lb facs="#facs_8_r1l17" n="15" break="no"/>ተከለልኮ፡ ወሲምኮውስተ<lb facs="#facs_8_r1l18" n="16" break="no"/>ኩሉ፡ ግብረ፡ ሰደዊከ፡ አባ<lb facs="#facs_8_r1l19" n="17" break="no"/>ግአኒ፡ ወኩሎአልሕመት፡ 
				<lb facs="#facs_8_r1l20" n="18"/>ወዓዶ፡አንሥሣ፡ ዘገዳም፡ አሰ<lb facs="#facs_8_r1l21" n="19" break="no"/>ወፈሰማይኒ፡ ወአስሐተባሕር<lb facs="#facs_8_r1l22" n="20" break="no"/>ወዘኒየሐውር፡ ውስተፍኖተ<lb facs="#facs_8_r1l23" n="21" break="no"/>ባሕር፡ እግዚኦ፡ እግዚእ፡ ጥቀ<lb facs="#facs_8_r1l24" n="22" break="no"/>ተስብሐአምከ፡ በኩሉም፡ድ<lb facs="#facs_8_r1l25" n="23" break="no"/>ር፡ አአምላከ፡ ዳዊዮኑ፡ አድ<lb facs="#facs_8_r1l26" n="24" break="no"/>ናለዓመትከ፡ መነን፡ መነን<lb facs="#facs_8_r1l28" n="25" break="no"/>ነ፡ ጸሎት በእንቲዘማ</ab>
         </div>
         <div type="textpart" subtype="image" n="9">
            <ab>
               <pb facs="#facs_9" n="9r"/>
               <cb facs="#facs_9_r1" n="a"/>
               <lb facs="#facs_9_r1l2" n="1" break="no"/>መ፡ ጽንዕት፡ ሰላም፡ በእሬህ<lb facs="#facs_9_r1l3" n="2" break="no"/>ከ፡ መክፈልተ፡ ሕማማት፡
				<lb facs="#facs_9_r1l4" n="3"/>ሰቁፍ ወቅናዋቲሁ፡ ይኤም<lb facs="#facs_9_r1l5" n="4" break="no"/>ህቦአፍኢየሱስ፡ ክርስቶስ፡ 
				<lb facs="#facs_9_r1l6" n="5"/>በላዕለ፡ ቅዱሳን፡ ዕሩፍ፡ ይጼ<lb facs="#facs_9_r1l7" n="6" break="no"/>ነከበው፡ ለተከርሣ፡ ዘናዓቃ<lb facs="#facs_9_r1l8" n="7" break="no"/>ልከ፡ መጽሐፍ፡ ፀዳልእም<lb facs="#facs_9_r1l9" n="8" break="no"/>ፀደልከመ፡ ቅጸንሰ፡ ሃፍ<lb facs="#facs_9_r1l10" n="9" break="no"/>ሰላም፡ ለጽንስትከ፡ ወለልደ<lb facs="#facs_9_r1l11" n="10" break="no"/>ትኮ፡ ምከርሥ፡ አመ፮ወ፬<lb facs="#facs_9_r1l12" n="11" break="no"/>ለወርሀታህሣሥ፡ ተከለሐ<lb facs="#facs_9_r1l13" n="12" break="no"/>ይማኖት፡ በኩሉ፡ ወበውሰተ፡
				<lb facs="#facs_9_r1l14" n="13"/>ኩሉ፡ሐዴሰ፡በስመ፡ አብወወ<lb facs="#facs_9_r1l15" n="14" break="no"/>ልድ፡ ወመንሬስ፡ ቅዱስ፡ ሰላም፡ 
				<lb facs="#facs_9_r1l16" n="15"/>ለጽንሰትከ፡ መሰረተ፡ ነገናወ<lb facs="#facs_9_r1l17" n="16" break="no"/>ውጣኔ ወበልደትከ፡ ሰላም፡
				<lb facs="#facs_9_r1l18" n="17"/>በብአራተ፡ መሬአክ፡ ሠናየ፡
				<lb facs="#facs_9_r1l19" n="18"/>ትኔገብር፡ መንፈስ፡ ቅድሳኒ፡
				<lb facs="#facs_9_r1l20" n="19"/>ውሎሰበኬ፡ ሐይማቶሙ፡ 
				<lb facs="#facs_9_r1l21" n="20"/>አተኩርንኔ፡ ተማህጸንኩ<lb facs="#facs_9_r1l22" n="21" break="no"/>አኪዳንከ፡ ከመኤይርያ፡ 
				<lb facs="#facs_9_r1l23" n="22"/>ኩነኔ ወበእንተዝሐሠሥ፡ 
				<lb facs="#facs_9_r1l24" n="23"/>ኬያከ፡ መድነኔ፡ ሰላም፡ ለሬ<lb facs="#facs_9_r1l25" n="24" break="no"/>ሣንከ እለኢያጸናዓ፡ አብሐ<lb facs="#facs_9_r1l26" n="25" break="no"/>ዘወበቃልእ፡ ግም፡ ለእስ<lb facs="#facs_9_r1l27" n="26" break="no"/>፯ንፍስከቢተፋኑኤልትጉ<lb facs="#facs_9_r1l28" n="27" break="no"/>ሕ፡ እንተተዓቅ፡ ነፍሳተ፡፡ለ</ab>
         </div>
         <div type="textpart" subtype="image" n="10">
            <ab>
               <pb facs="#facs_10" n="10r"/>
               <cb facs="#facs_10_r3" n="a"/>
               <lb facs="#facs_10_r3l5" n="1" break="no"/>ሕ፡ እንተተዓቅብ፡ ነፍሳተለ<lb facs="#facs_10_r3l6" n="2" break="no"/>ስብእወበእንሥሣ፡ ሉታሔ<lb facs="#facs_10_r3l7" n="3" break="no"/>ማህጸኖሙ፡ አንተ፡ ጽላሎ<lb facs="#facs_10_r3l8" n="4" break="no"/>ኑከ፡ ታነኦዕ፡ ምውተ፡ አድ<lb facs="#facs_10_r3l9" n="5" break="no"/>ህና እምህማመ፡ ዘርወ<lb facs="#facs_10_r3l10" n="6" break="no"/>ወለጅመነኛወጉሥም፡ 
				<lb facs="#facs_10_r3l11" n="7"/>ትፌራ፡ ወንዳድ፡ እጅሰብ፡ 
				<lb facs="#facs_10_r3l12" n="8"/>እ፡ ወጽላዋጊ፡ ማርተኛወ<lb facs="#facs_10_r3l13" n="9" break="no"/>ተጸበኛ፡ ወእምህማመ፡ 
				<lb facs="#facs_10_r3l14" n="10"/>ደም፡ አድህና፡ለዓመተ<lb facs="#facs_10_line_1724841644591_576" n="11" break="no"/>ከ፡ መነ[  ] ልልልል[ ]</ab>
         </div>
         <div type="textpart" subtype="image" n="11">
            <ab>
               <pb facs="#facs_11" n="11r"/>
               <cb facs="#facs_11_tr_1" n="a"/>
               <lb facs="#facs_11_tr_1_tl_1" n="1" break="no"/>
            </ab>
         </div>
         <div type="textpart" subtype="image" n="12">
            <ab>
               <pb facs="#facs_12" n="12r"/>
            </ab>
         </div>
      </div>
   </body>
</text>
